gputools/__init__.py
gputools/__main__.py
gputools/version.py
gputools/config/__init__.py
gputools/config/config.py
gputools/config/myconfigparser.py
gputools/convolve/__init__.py
gputools/convolve/_abspath.py
gputools/convolve/_lapgauss.py
gputools/convolve/convolve.py
gputools/convolve/convolve_sep.py
gputools/convolve/convolve_spatial2.py
gputools/convolve/convolve_spatial3.py
gputools/convolve/convolve_spatial_old.py
gputools/convolve/correlate.py
gputools/convolve/gaussian_filter.py
gputools/convolve/generic_separable_filters.py
gputools/convolve/median_filter.py
gputools/convolve/kernels/conv_spatial2.cl
gputools/convolve/kernels/conv_spatial3.cl
gputools/convolve/kernels/convolve.cl
gputools/convolve/kernels/convolve1.cl
gputools/convolve/kernels/convolve2.cl
gputools/convolve/kernels/convolve3.cl
gputools/convolve/kernels/convolve_sep.cl
gputools/convolve/kernels/correlate_kernels.cl
gputools/convolve/kernels/generic_separable_filter.cl
gputools/convolve/kernels/median_filter.cl
gputools/core/__init__.py
gputools/core/cl_error_codes.py
gputools/core/oclalgos.py
gputools/core/ocldevice.py
gputools/core/oclmultireduction.py
gputools/core/oclprogram.py
gputools/core/ocltypes.py
gputools/core/kernels/copy_resampled.cl
gputools/deconv/__init__.py
gputools/deconv/_abspath.py
gputools/deconv/deconv_rl.py
gputools/deconv/deconv_rl_spatial.py
gputools/deconv/kernels/deconv_rl.cl
gputools/denoise/__init__.py
gputools/denoise/_abspath.py
gputools/denoise/bilateral2.py
gputools/denoise/bilateral3.py
gputools/denoise/nlm2.py
gputools/denoise/nlm3.py
gputools/denoise/tv2.py
gputools/denoise/kernels/bilateral2.cl
gputools/denoise/kernels/bilateral3.cl
gputools/denoise/kernels/bilateralAdapt.cl
gputools/denoise/kernels/bilateral_shared.cl
gputools/denoise/kernels/dct_8x8.cl
gputools/denoise/kernels/dct_8x8_new.cl
gputools/denoise/kernels/dct_8x8x8.cl
gputools/denoise/kernels/nlm2.cl
gputools/denoise/kernels/nlm3.cl
gputools/denoise/kernels/nlm3_thresh.cl
gputools-0.2.14.dist-info/LICENSE.txt
gputools-0.2.14.dist-info/METADATA
gputools-0.2.14.dist-info/WHEEL
gputools-0.2.14.dist-info/top_level.txt
gputools-0.2.14.dist-info/RECORD
