Metadata-Version: 2.1
Name: gputools
Version: 0.2.14
Summary: OpenCL accelerated volume processing
Home-page: https://github.com/maweigert/gputools
Author: Martin Weigert
Author-email: martin.weigert@epfl.ch
License: BSD 3-Clause License
Keywords: science image-processing
Classifier: Development Status :: 3 - Alpha
Classifier: Intended Audience :: Science/Research
Classifier: Topic :: Software Development
Classifier: Topic :: Scientific/Engineering
Classifier: License :: OSI Approved :: BSD License
Classifier: Programming Language :: Python :: 2.7
Classifier: Programming Language :: Python :: 3.5
Classifier: Programming Language :: Python :: 3.6
Classifier: Programming Language :: Python :: 3.8
Classifier: Programming Language :: Python :: 3.9
Classifier: Programming Language :: Python :: 3.10
License-File: LICENSE.txt
Requires-Dist: six
Requires-Dist: scipy
Requires-Dist: numpy (<1.24.0)
Requires-Dist: pyopencl (>=2016.1)
Requires-Dist: configparser
Requires-Dist: reikna (>=0.6.7)
Requires-Dist: scikit-tensor ; python_version<"3.0"
Requires-Dist: ConfigParser ; python_version<"3.0"
Requires-Dist: configparser ; python_version>="3.0"
